<images xmlns="http://www.gutenberg.ph/2006/schemas/imageinfo">
<image path="images/new-cover.jpg" filesize="237651" filedate="2023-09-10 13:08:25" width="960px" height="1440px"/>
<image path="images/p000.jpg" filesize="394347" filedate="2023-09-10 13:08:25" width="1019px" height="1440px"/>
<image path="images/p001.jpg" filesize="342996" filedate="2023-09-10 13:08:25" width="998px" height="1440px"/>
<image path="images/p009.jpg" filesize="357129" filedate="2023-09-10 13:08:25" width="1004px" height="1440px"/>
<image path="images/p022.jpg" filesize="322226" filedate="2023-09-10 13:08:25" width="998px" height="1440px"/>
<image path="images/p043.jpg" filesize="386411" filedate="2023-09-10 13:08:25" width="1010px" height="1440px"/>
<image path="images/p056.jpg" filesize="320952" filedate="2023-09-10 13:08:25" width="1009px" height="1440px"/>
<image path="images/p062.jpg" filesize="351292" filedate="2023-09-10 13:08:25" width="1019px" height="1440px"/>
<image path="images/p077.jpg" filesize="323299" filedate="2023-09-10 13:08:25" width="1020px" height="1440px"/>
<image path="images/p090.jpg" filesize="320197" filedate="2023-09-10 13:08:25" width="998px" height="1440px"/>
<image path="images/p095.jpg" filesize="348388" filedate="2023-09-10 13:08:25" width="1008px" height="1440px"/>
<image path="images/p106.jpg" filesize="307336" filedate="2023-09-10 13:08:25" width="997px" height="1440px"/>
<image path="images/p117.jpg" filesize="314637" filedate="2023-09-10 13:08:25" width="987px" height="1440px"/>
<image path="images/p123.jpg" filesize="364537" filedate="2023-09-10 13:08:25" width="996px" height="1440px"/>
<image path="images/p138.jpg" filesize="362275" filedate="2023-09-10 13:08:25" width="1440px" height="998px"/>
<image path="images/p141.jpg" filesize="360870" filedate="2023-09-10 13:08:25" width="1440px" height="1016px"/>
<image path="images/p145.jpg" filesize="380679" filedate="2023-09-10 13:08:25" width="1005px" height="1440px"/>
<image path="images/p162.jpg" filesize="360194" filedate="2023-09-10 13:08:25" width="1440px" height="1001px"/>
<image path="images/p170.jpg" filesize="345623" filedate="2023-09-10 13:08:25" width="1024px" height="1440px"/>
<image path="images/p174.jpg" filesize="375697" filedate="2023-09-10 13:08:25" width="1440px" height="1009px"/>
<image path="images/p181.jpg" filesize="376238" filedate="2023-09-10 13:08:25" width="1440px" height="1016px"/>
<image path="images/p188.jpg" filesize="368364" filedate="2023-09-10 13:08:25" width="1017px" height="1440px"/>
<image path="images/p194.jpg" filesize="398313" filedate="2023-09-10 13:08:25" width="1440px" height="1006px"/>
<image path="images/p210.jpg" filesize="346372" filedate="2023-09-10 13:08:25" width="1440px" height="1018px"/>
<image path="images/p214.jpg" filesize="338688" filedate="2023-09-10 13:08:25" width="1440px" height="1002px"/>
<image path="images/p216.jpg" filesize="321152" filedate="2023-09-10 13:08:25" width="1440px" height="1025px"/>
<image path="images/p218.jpg" filesize="407035" filedate="2023-09-10 13:08:25" width="1440px" height="1019px"/>
<image path="images/p237.jpg" filesize="400284" filedate="2023-09-10 13:08:25" width="1016px" height="1440px"/>
<image path="images/p238.jpg" filesize="358394" filedate="2023-09-10 13:08:25" width="1440px" height="1010px"/>
<image path="images/p248.jpg" filesize="376699" filedate="2023-09-10 13:08:25" width="1015px" height="1440px"/>
<image path="images/p259.jpg" filesize="355332" filedate="2023-09-10 13:08:25" width="990px" height="1440px"/>
<image path="images/p266.jpg" filesize="347855" filedate="2023-09-10 13:08:25" width="1013px" height="1440px"/>
<image path="images/p271.jpg" filesize="309295" filedate="2023-09-10 13:08:25" width="1017px" height="1440px"/>
<image path="images/qr38488.png" filesize="324" filedate="2023-09-10 13:08:48" width="296px" height="296px"/>
<image path="images/titlepage.png" filesize="20464" filedate="2023-09-10 13:08:25" width="926px" height="1440px"/>
</images>